arraydb/__init__.py
arraydb/_version.py
arraydb/database.py
arraydb/types.py
arraydb-0.1.1.dist-info/METADATA
arraydb-0.1.1.dist-info/WHEEL
arraydb-0.1.1.dist-info/top_level.txt
arraydb-0.1.1.dist-info/RECORD
