Metadata-Version: 2.1
Name: arraydb
Version: 0.1.1
Summary: Database using array. With an basic ORM
Home-page: https://github.com/shahriyardx/arraydb
Author: Md Shahriyar Alam
Author-email: contact@shahriyar.dev
License: MIT
Keywords: arraydb,database
Classifier: Development Status :: 4 - Beta
Classifier: Intended Audience :: Developers
Classifier: Natural Language :: English
Classifier: License :: OSI Approved :: MIT License
Classifier: Programming Language :: Python
Classifier: Programming Language :: Python :: 3
Classifier: Programming Language :: Python :: 3.6
Classifier: Programming Language :: Python :: 3.7
Classifier: Programming Language :: Python :: 3.8
Classifier: Topic :: Database
Classifier: Operating System :: OS Independent
Requires-Python: >=3.6
Requires-Dist: cuid (==0.4)
Requires-Dist: typing-extensions (==4.5.0)
